{
  "$schema": "https://biomejs.dev/schemas/2.4.8/schema.json",
  "linter": {
    "enabled": true,
    "rules": {
      "recommended": true,
      "style": {
        "noNonNullAssertion": "off",
        "useConst": "error",
        "useNodejsImportProtocol": "off"
      },
      "suspicious": {
        "noExplicitAny": "off",
        "noControlCharactersInRegex": "off",
        "noEmptyInterface": "off"
      }
    }
  },
  "formatter": {
    "enabled": true,
    "formatWithErrors": false,
    "indentStyle": "space",
    "indentWidth": 2,
    "lineWidth": 80
  },
  "files": {
    "includes": [
      "packages/*/src/**/*.ts",
      "packages/*/test/**/*.ts",
      "packages/coding-agent/examples/**/*.ts",
      "packages/web-ui/src/**/*.ts",
      "packages/web-ui/example/**/*.ts",
      "!**/node_modules/**/*",
      "!**/test-sessions.ts",
      "!**/models.generated.ts",
      "!packages/web-ui/src/app.css",
      "!packages/mom/data/**/*",
      "!!**/node_modules"
    ]
  }
}
